funtools/__init__.py
funtools/__main__.py
funtools/main.py
funtools-0.1.0.dist-info/LICENSE
funtools-0.1.0.dist-info/WHEEL
funtools-0.1.0.dist-info/METADATA
funtools-0.1.0.dist-info/RECORD
