Metadata-Version: 2.1
Name: funtools
Version: 0.1.0
Summary: Useful fun tools
License: MIT
Author: ischaojie
Author-email: zhuzhezhe95@gmail.com
Requires-Python: >=3.10,<4.0
Classifier: License :: OSI Approved :: MIT License
Classifier: Programming Language :: Python :: 3
Classifier: Programming Language :: Python :: 3.10
Requires-Dist: click (>=8.1.3,<9.0.0)
Requires-Dist: rich (>=12.5.1,<13.0.0)
